nestipy/__init__.py
nestipy/commander/__init__.py
nestipy/commander/abstract.py
nestipy/commander/commander.py
nestipy/commander/decorator.py
nestipy/commander/factory.py
nestipy/commander/meta.py
nestipy/commander/style.py
nestipy/common/__init__.py
nestipy/common/logger.py
nestipy/common/utils.py
nestipy/common/config/__init__.py
nestipy/common/config/config_builder.py
nestipy/common/config/config_module.py
nestipy/common/config/config_service.py
nestipy/common/decorator/__init__.py
nestipy/common/decorator/class_.py
nestipy/common/decorator/method.py
nestipy/common/decorator/tests/test_class.py
nestipy/common/exception/__init__.py
nestipy/common/exception/decorator.py
nestipy/common/exception/http.py
nestipy/common/exception/interface.py
nestipy/common/exception/message.py
nestipy/common/exception/meta.py
nestipy/common/exception/status.py
nestipy/common/guards/__init__.py
nestipy/common/guards/can_activate.py
nestipy/common/guards/decorator.py
nestipy/common/guards/meta.py
nestipy/common/helpers/__init__.py
nestipy/common/http_/__init__.py
nestipy/common/http_/form_parsers.py
nestipy/common/http_/multipart.py
nestipy/common/http_/request.py
nestipy/common/http_/response.py
nestipy/common/http_/test.py
nestipy/common/http_/upload_file.py
nestipy/common/http_/websocket.py
nestipy/common/interceptor/__init__.py
nestipy/common/interceptor/decorator.py
nestipy/common/interceptor/interface.py
nestipy/common/interceptor/meta.py
nestipy/common/middleware/__init__.py
nestipy/common/middleware/cors.py
nestipy/common/middleware/helmet.py
nestipy/common/middleware/interface.py
nestipy/common/middleware/meta.py
nestipy/common/middleware/session.py
nestipy/common/template/__init__.py
nestipy/common/template/decorator.py
nestipy/common/template/interface.py
nestipy/common/template/meta.py
nestipy/core/__init__.py
nestipy/core/constant.py
nestipy/core/instance_loader.py
nestipy/core/nestipy_application.py
nestipy/core/nestipy_factory.py
nestipy/core/nestipy_microservice.py
nestipy-0.8.0.dist-info/METADATA
nestipy-0.8.0.dist-info/WHEEL
nestipy-0.8.0.dist-info/licenses/LICENSE
nestipy-0.8.0.dist-info/RECORD
