Metadata-Version: 2.4
Name: nestipy
Version: 0.8.0
Summary: Nestipy is a Python framework built on top of BlackSheep that follows the modular architecture of NestJS
Author-email: tsiresymila <tsiresymila@gmail.com>
License-File: LICENSE
Requires-Python: <4,>=3.11
Requires-Dist: aio-pika<10,>=9.4.3
Requires-Dist: aiofiles<25,>=24.1.0
Requires-Dist: aiomqtt<3,>=2.3.0
Requires-Dist: async-timeout<6,>=5.0.1
Requires-Dist: asyncclick<9,>=8.1.7.2
Requires-Dist: chardet<6,>=5.2.0
Requires-Dist: click<9,>=8.1.7
Requires-Dist: dataclasses-json<0.7,>=0.6.7
Requires-Dist: dotenv>=0.9.9
Requires-Dist: essentials<2,>=1.1.5
Requires-Dist: fastapi>=0.116.1
Requires-Dist: grpcio-tools<2,>=1.74.0
Requires-Dist: grpcio<2,>=1.74.0
Requires-Dist: httpx<0.28,>=0.27.2
Requires-Dist: itsdangerous<3,>=2.2.0
Requires-Dist: jinja2<4,>=3.1.4
Requires-Dist: minijinja<3,>=2.5.0
Requires-Dist: nats-py<3,>=2.9.0
Requires-Dist: orjson>=3.11.1
Requires-Dist: pydantic[email]>=2.11.7
Requires-Dist: pyee<13,>=12.1.1
Requires-Dist: python-multipart<0.0.18,>=0.0.17
Requires-Dist: python-socketio<6,>=5.11.1
Requires-Dist: pyyaml<7,>=6.0.2
Requires-Dist: redis<6,>=5.2.0
Requires-Dist: rich<15,>=14.1.0
Requires-Dist: snakecase<2,>=1.0.1
Requires-Dist: strawberry-graphql>=0.278.0
Requires-Dist: ujson<6,>=5.9.0
Provides-Extra: blacksheep
